{
	"Changes": [

		{
			"Action": "Load",
			"Target": "Characters/Gunther, Portraits/Gunther",
			"FromFile": "assets/{{Target}}{{Random: black |key={{TargetWithoutPath}}}}.png",
			"Update": "OnDayStart",
			"When": {
				"Season": "Summer, Spring, Fall"
			}
		},
		{
			"Action": "Load",
			"Target": "Characters/Gunther, Portraits/Gunther",
			"FromFile": "assets/{{Target}}{{Random: black |key={{TargetWithoutPath}}}}.png",
			"Update": "OnDayStart",
			"When": {
				"Season": "Winter"
			}
		},
		{
			"Action": "EditImage",
			"Target": "Characters/Gunther_Winter",
			"FromFile": "assets/Characters/Gunther_Winter.png"
		},
		{
			"Action": "EditImage",
			"Target": "Portraits/Gunther_Winter",
			"FromFile": "assets/Portraits/Gunther_Winter.png"
		},

		{
			"Action": "EditImage",
			"Target": "Characters/Gunther_Beach",
			"FromFile": "assets/Characters/Gunther_Beach.png"
		},
		{
			"Action": "EditImage",
			"Target": "Portraits/Gunther_Beach",
			"FromFile": "assets/Portraits/Gunther_Beach.png"
		}
		//{
		//	"Action": "EditData",
		//	"Target": "Characters/schedules/Penny",
		//	"Entries": {}

		//}


		//{
		//	"Action": "Load",
		//	"Target": "Characters/Penny",
		//	"FromFile": "assets/Characters/Nami.png"
		//},
		//{
		//	"Action": "Load",
		//	"Target": "Portraits/Penny",
		//	"FromFile": "assets/Characters/Nami.png"
		//},
	]

}