{
	"Changes": [
		
		{
			"Action": "EditImage",
			"Target": "Characters/Krobus",
			"FromFile": "assets/Characters/Chopper.png"
		},
		{
			"Action": "EditImage",
			"Target": "Portraits/Krobus",
			"FromFile": "assets/Portraits/Custom/Chopper.png"
		}
		//{
		//	"Action": "EditData",
		//	"Target": "Characters/schedules/Penny",
		//	"Entries": {}

		//}


		//{
		//	"Action": "Load",
		//	"Target": "Characters/Penny",
		//	"FromFile": "assets/Characters/Nami.png"
		//},
		//{
		//	"Action": "Load",
		//	"Target": "Portraits/Penny",
		//	"FromFile": "assets/Characters/Nami.png"
		//},
	]

}